huitzo_sdk/__init__.py
huitzo_sdk/client.py
huitzo_sdk/cron.py
huitzo_sdk/email.py
huitzo_sdk/exceptions.py
huitzo_sdk/llm.py
huitzo_sdk/models.py
huitzo_sdk/sites.py
huitzo_sdk-1.0.20251110.dist-info/METADATA
huitzo_sdk-1.0.20251110.dist-info/WHEEL
huitzo_sdk-1.0.20251110.dist-info/top_level.txt
huitzo_sdk-1.0.20251110.dist-info/RECORD
