Metadata-Version: 2.4
Name: huitzo-sdk
Version: 1.0.20251110
Summary: Developer SDK for Huitzo WebCLI Platform Tools
Author-email: Huitzo Team <support@huitzo.com>
License: MIT
Project-URL: Homepage, https://huitzo.com
Project-URL: Documentation, https://docs.huitzo.com
Project-URL: Repository, https://github.com/huitzo/huitzo-sdk
Project-URL: Issues, https://github.com/huitzo/huitzo-sdk/issues
Keywords: huitzo,sdk,api,cron,email,developer-tools
Classifier: Development Status :: 4 - Beta
Classifier: Intended Audience :: Developers
Classifier: License :: OSI Approved :: MIT License
Classifier: Programming Language :: Python :: 3
Classifier: Programming Language :: Python :: 3.10
Classifier: Programming Language :: Python :: 3.11
Classifier: Programming Language :: Python :: 3.12
Classifier: Topic :: Software Development :: Libraries :: Python Modules
Requires-Python: >=3.10
Requires-Dist: aiohttp<4.0.0,>=3.9.0
Requires-Dist: pydantic<3.0.0,>=2.5.0
Provides-Extra: dev
Requires-Dist: pytest>=7.4.0; extra == "dev"
Requires-Dist: pytest-asyncio>=0.21.0; extra == "dev"
Requires-Dist: pytest-cov>=4.1.0; extra == "dev"
Requires-Dist: aioresponses>=0.7.6; extra == "dev"
Requires-Dist: black>=23.0.0; extra == "dev"
Requires-Dist: ruff>=0.1.0; extra == "dev"
Requires-Dist: mypy>=1.5.0; extra == "dev"
